LICENSE.txt
setup.py
CCNN.egg-info/PKG-INFO
CCNN.egg-info/SOURCES.txt
CCNN.egg-info/dependency_links.txt
CCNN.egg-info/requires.txt
CCNN.egg-info/top_level.txt
code/__init__.py