Metadata-Version: 2.1
Name: CCNN
Version: 0.1.0
Summary: Q Network Implementation
Home-page: UNKNOWN
Author: Hamza Mehyedden
License: UNKNOWN
Platform: UNKNOWN
Classifier: Programming Language :: Python :: 3.6
Classifier: Operating System :: OS Independent
Classifier: License :: OSI Approved :: MIT License
Requires-Python: >=3.6
License-File: LICENSE.txt
